sniplink/__init__.py
sniplink/api.py
sniplink/client.py
sniplink/objects.py
sniplink/utils.py
sniplink-1.0.0.dist-info/LICENSE.md
sniplink-1.0.0.dist-info/METADATA
sniplink-1.0.0.dist-info/WHEEL
sniplink-1.0.0.dist-info/top_level.txt
sniplink-1.0.0.dist-info/RECORD
