Metadata-Version: 2.1
Name: sniplink
Version: 1.0.0
Summary: API wrapper for the SnipLink API provided by SnipLink.
Home-page: https://github.com/billyeatcookies/sniplink-py
Author: billyeatcookies
Author-email: billydevbusiness@gmail.com
License: MIT
Keywords: api wrapper python3 python sniplink sniplink.py sniplink-py
Platform: UNKNOWN
Classifier: License :: OSI Approved :: MIT License
Classifier: Programming Language :: Python :: 3
Classifier: Programming Language :: Python :: 3.8
Classifier: Operating System :: OS Independent
License-File: LICENSE.md
Requires-Dist: requests
